{
  "project_info": {
    "project_number": "685408741619",
    "project_id": "eguru-mad-project",
    "storage_bucket": "eguru-mad-project.appspot.com"
  },
  "client": [
    {
      "client_info": {
        "mobilesdk_app_id": "1:685408741619:android:4a57746adcd3a37fa1ef86",
        "android_client_info": {
          "package_name": "com.example.eguru_madproject"
        }
      },
      "oauth_client": [
        {
          "client_id": "685408741619-34e1vpi4dg6qojfhjtvlggqkq49r63p4.apps.googleusercontent.com",
          "client_type": 3
        }
      ],
      "api_key": [
        {
          "current_key": "AIzaSyDRcakJu58-fY5GqeOVKfs2VHy4fmBnlD8"
        }
      ],
      "services": {
        "appinvite_service": {
          "other_platform_oauth_client": [
            {
              "client_id": "685408741619-34e1vpi4dg6qojfhjtvlggqkq49r63p4.apps.googleusercontent.com",
              "client_type": 3
            }
          ]
        }
      }
    }
  ],
  "configuration_version": "1"
}